setup.py
survey/__init__.py
survey/actions.py
survey/admin.py
survey/forms.py
survey/models.py
survey/signals.py
survey/urls.py
survey/utils.py
survey/views.py
survey/widgets.py
survey/migrations/0001_initial.py
survey/migrations/0002_survey_template.py
survey/migrations/0003_auto_20160313_2126.py
survey/migrations/__init__.py
survey/south_migrations/0001_initial.py
survey/south_migrations/0002_auto__add_field_category_order.py
survey/south_migrations/__init__.py
survey/templatetags/__init__.py
survey/templatetags/survey_extras.py
tanuki.egg-info/PKG-INFO
tanuki.egg-info/SOURCES.txt
tanuki.egg-info/dependency_links.txt
tanuki.egg-info/requires.txt
tanuki.egg-info/top_level.txt
tests/__init__.py
tests/models.py
tests/settings.py
tests/tests/__init__.py
tests/tests/test_models.py
tests/tests/test_utils.py
tests/tests/test_views.py