Metadata-Version: 1.1
Name: tanuki
Version: 0.1.6
Summary: Create dynamic forms in Django
Home-page: https://github.com/jibaku/tanuki/
Author: Fabien Schwob
Author-email: github@x-phuture.com
License: AGPL
Platform: UNKNOWN
Classifier: Development Status :: 3 - Alpha
Classifier: Environment :: Web Environment
Classifier: Intended Audience :: Developers
Classifier: License :: OSI Approved :: GNU Affero General Public License v3
Classifier: Operating System :: OS Independent
Classifier: Programming Language :: Python
Classifier: Framework :: Django
